odslib3/__init__.py
odslib3/odsContent.py
odslib3/odsManifest.py
odslib3/odsMeta.py
odslib3/odsMimetype.py
odslib3/odsSettings.py
odslib3/odsStyles.py
odslib3/odsXML.py
odslib3-1.2.0.post2.dist-info/DESCRIPTION.rst
odslib3-1.2.0.post2.dist-info/METADATA
odslib3-1.2.0.post2.dist-info/RECORD
odslib3-1.2.0.post2.dist-info/WHEEL
odslib3-1.2.0.post2.dist-info/metadata.json
odslib3-1.2.0.post2.dist-info/top_level.txt
