Metadata-Version: 2.0
Name: odslib3
Version: 1.2.0.post2
Summary: An easy to use module that creates ODS documents.
Home-page: https://github.com/Exelscior/odslib3
Author: Joshua Logan
Author-email: joshua.logan@eveco.re
License: GPL
Keywords: ods libreoffice
Platform: UNKNOWN
Classifier: Development Status :: 5 - Production/Stable
Classifier: Environment :: Plugins
Classifier: Intended Audience :: Developers
Classifier: License :: OSI Approved :: GNU General Public License (GPL)
Classifier: Operating System :: OS Independent
Classifier: Natural Language :: English
Classifier: Programming Language :: Python :: 2.7
Classifier: Programming Language :: Python :: 3
Classifier: Programming Language :: Python :: 3.5
Classifier: Programming Language :: Python :: 3.6
Classifier: Topic :: Software Development :: Libraries :: Python Modules
Requires-Python: >=2.7
